pranerpacker/__init__.py
pranerpacker/basepranee.py
pranerpacker-0.0.2.dist-info/METADATA
pranerpacker-0.0.2.dist-info/WHEEL
pranerpacker-0.0.2.dist-info/top_level.txt
pranerpacker-0.0.2.dist-info/RECORD
