Metadata-Version: 2.1
Name: pranerpacker
Version: 0.0.2
Summary: Praneeths first Python package
Author: Sai Praneeth Renduchinthala
Author-email: praneeth.renduchinthala210@gmail.com
Keywords: pranerpacker
Classifier: Development Status :: 3 - Alpha
Classifier: Intended Audience :: Education
Classifier: Programming Language :: Python :: 2
Classifier: Programming Language :: Python :: 3
Classifier: Operating System :: MacOS :: MacOS X
Classifier: Operating System :: Microsoft :: Windows
